{
	"name":"World Server",
	"version":1,
	"description":"All-in-one 'world' incl. mongodb, rabbitmq, memcached, nginx, and more.",
	"env" : "Disposable",
	"isProd" : false,
	"isContainer" : true,
	"facilities":{
		"http":{
			"port":HTTP_PORT
		},
		"storage":{
			"mongoDB":{
				"uris":["HOSTIP:MONGO_PORT"]
			}
		},
		"queue":{
			"rabbitMQ":{
				"host":"HOSTIP",
				"port":"RABBIT_PORT"
			}
		},
		"cache":{
			"memcached":{
				"uris":["HOSTIP:MEMCACHE_PORT"]
			}
		}
	},
	"applications":[
	]
}
